cards_deck/__init__.py
cards_deck/_modidx.py
cards_deck/card.py
cards_deck/deck.py
cards_deck-0.0.3.dist-info/LICENSE
cards_deck-0.0.3.dist-info/METADATA
cards_deck-0.0.3.dist-info/WHEEL
cards_deck-0.0.3.dist-info/entry_points.txt
cards_deck-0.0.3.dist-info/top_level.txt
cards_deck-0.0.3.dist-info/RECORD
