Metadata-Version: 2.1
Name: cards-deck
Version: 0.0.3
Summary: An example repository for nbdev
Home-page: https://github.com/fastai/cards_deck
Author: Isaac Flath and Jeremy Howard
Author-email: info@fast.ai
License: Apache Software License 2.0
Keywords: nbdev
Classifier: Development Status :: 3 - Alpha
Classifier: Intended Audience :: Developers
Classifier: Natural Language :: English
Classifier: Programming Language :: Python :: 3.7
Classifier: Programming Language :: Python :: 3.8
Classifier: License :: OSI Approved :: Apache Software License
Requires-Python: >=3.7
License-File: LICENSE
Requires-Dist: fastcore
Provides-Extra: dev
Requires-Dist: plotly ; extra == 'dev'
Requires-Dist: pandas ; extra == 'dev'
Requires-Dist: nbformat (>=4.2.0) ; extra == 'dev'
